lockfilesmith/__init__.py
lockfilesmith/exceptions.py
lockfilesmith/models.py
lockfilesmith/cmds/__init__.py
lockfilesmith/cmds/install.py
lockfilesmith/cmds/lock.py
lockfilesmith/cmds/query.py
lockfilesmith/cmds/sync.py
lock_file_smith-0.1.0.dist-info/LICENSE
lock_file_smith-0.1.0.dist-info/METADATA
lock_file_smith-0.1.0.dist-info/WHEEL
lock_file_smith-0.1.0.dist-info/top_level.txt
lock_file_smith-0.1.0.dist-info/zip-safe
lock_file_smith-0.1.0.dist-info/RECORD
