Metadata-Version: 2.1
Name: lock-file-smith
Version: 0.1.0
Summary: Simple wrapper for Git LFS (Large File Storage) commands.
Home-page: https://github.com/hueyyeng/lock-file-smith
Author: Huey Yeng
Author-email: Huey Yeng <huey.yeng.mmu@gmail.com>
Maintainer: Huey Yeng
Maintainer-email: Huey Yeng <huey.yeng.mmu@gmail.com>
License: MIT License
Project-URL: Homepage, https://github.com/hueyyeng/lock-file-smith
Project-URL: Bug Reports, https://github.com/hueyyeng/lock-file-smith/issues
Project-URL: Source, https://github.com/hueyyeng/lock-file-smith
Keywords: python,library,git,lfs
Classifier: Intended Audience :: Developers
Classifier: Programming Language :: Python :: 3.11
Classifier: Programming Language :: Python :: 3.10
Classifier: Programming Language :: Python :: 3.9
Classifier: Programming Language :: Python :: 3.8
Classifier: Operating System :: MacOS
Classifier: Operating System :: POSIX :: Linux
Classifier: Operating System :: Microsoft :: Windows :: Windows 10
Requires-Python: >=3.8
License-File: LICENSE
